md_streamer/__init__.py
md_streamer/stream_md_to_html.py
md_streamer-0.1.0.dist-info/licenses/LICENSE
md_streamer-0.1.0.dist-info/METADATA
md_streamer-0.1.0.dist-info/WHEEL
md_streamer-0.1.0.dist-info/top_level.txt
md_streamer-0.1.0.dist-info/RECORD
